hypixelpy/__init__.py
hypixelpy/api.py
hypixelpy/exceptions.py
hypixelpy/gametypes.json
hypixelpy/gametypes.py
hypixelpy/hypixel.py
hypixelpy/other.py
hypixelpy/player.py
hypixelpy/resources.py
hypixelpy/skyblock.py
hypixelpy-0.1.1.dist-info/LICENSE
hypixelpy-0.1.1.dist-info/METADATA
hypixelpy-0.1.1.dist-info/WHEEL
hypixelpy-0.1.1.dist-info/top_level.txt
hypixelpy-0.1.1.dist-info/RECORD
