Metadata-Version: 2.1
Name: hypixelpy
Version: 0.1.1
Summary: A simple wrapper for Hypixel API
Home-page: https://github.com/cinget/hypixelpy
Author: cinget
Author-email: evertonpassine@gmail.com
License: UNKNOWN
Project-URL: Bug Tracker, https://github.com/cinget/hypixelpy/issues
Project-URL: Wiki, https://github.com/cinget/hypixelpy/wiki
Platform: UNKNOWN
Classifier: Programming Language :: Python :: 3 
Classifier: License :: OSI Approved :: GNU General Public License v3 (GPLv3)
Classifier: Operating System :: OS Independent
Requires-Python: >=3.6
Requires-Dist: requests
